scripta/__init__.py
scripta/__main__.py
scripta/cast.py
scripta/cast_recorder.py
scripta/colors.py
scripta/constants.py
scripta/line.py
scripta/run.py
scripta/stable_hash.py
scripta/times.py
scripta/typing_errors.py
scripta/upload.py
scripta/waiter.py
scripta-0.9.1.data/scripts/scripta
scripta-0.9.1.dist-info/LICENSE
scripta-0.9.1.dist-info/METADATA
scripta-0.9.1.dist-info/WHEEL
scripta-0.9.1.dist-info/top_level.txt
scripta-0.9.1.dist-info/RECORD
